{
    "katello": "4.9",
    "builds": [
        {
            "title": "Katello on EL",
            "header": "Foreman {FOREMAN_VER} and Katello {KATELLO_VER}",
            "filename": "index-katello.html",
            "sections": {
                "Release notes and upgrading": [
                    ["Release_Notes", "Release Notes"],
                    ["Upgrading_Project", "Upgrading Katello to 4.9"]
                ],
                "Quickstart": [
                    ["Quickstart", "Quickstart Guide"]
                ],
                "Deploying Foreman and Katello": [
                    ["Planning_for_Project", "Planning Guide"],
                    ["Installing_Server", "Installing Katello Server"],
                    ["Installing_Proxy", "Installing Smart Proxy with Content"],
                    ["Configuring_Load_Balancer", "Configuring Smart Proxies with a Load Balancer"],
                    ["Deploying_Project_on_AWS", "Deploying Foreman on AWS"]
                ],
                "Administering Foreman server": [
                    ["Administering_Project", "Administering Foreman"],
                    ["Managing_Organizations_and_Locations", "Managing Organizations and Locations in Foreman"],
                    ["Managing_Content", "Managing Content"],
                    ["Tuning_Performance", "Tuning Performance"]
                ],
                "Administering hosts": [
                    ["Provisioning_Hosts", "Provisioning Hosts"],
                    ["Managing_Hosts", "Managing Hosts"],
                    ["Managing_Configurations_Ansible", "Configuring Hosts Using Ansible"],
                    ["Managing_Configurations_Puppet", "Configuring Hosts Using Puppet"],
                    ["Managing_Configurations_Salt", "Configuring Hosts Using Salt"],
                    ["Managing_Security_Compliance", "Managing Security Compliance"],
                    ["Deploying_Hosts_AppCentric", "Application Centric Deployment"]
                ]
            }
        }
    ]
}
